{
    "Awesome Background": {
        "prefix": ["container"],
        "body": [
            "widget = wibox.container.background,", "$0"
        ],
        "description": "Wibox container 'margin'."
    },
    "Awesome Margins": {
        "prefix": ["margin"],
        "body": [
            "widget = wibox.container.margin,", "$0"
        ],
        "description": "Wibox container 'margin'."
    },
    "Awesome Layout Align": {
        "prefix": ["align"],
        "body": [
            "layout = wibox.layout.align.horizontal,", "$0"
        ],
        "description": "Wibox layout 'align.horizontal'."
    },
    "Awesome Layout Fixed": {
        "prefix": ["fixed"],
        "body": [
            "layout = wibox.layout.fixed.horizontal,", "$0"
        ],
        "description": "Wibox layout 'fixed.horizontal'."
    },
    "Awesome Layout Flex": {
        "prefix": ["flex"],
        "body": [
            "layout = wibox.layout.flex.horizontal,", "$0"
        ],
        "description": "Wibox layout 'flex.horizontal'."
    }
}
